imprimatur/__init__.py
imprimatur/_version.py
imprimatur/api.py
imprimatur/console.py
imprimatur/web.py
imprimatur/templates/base.html
imprimatur/templates/home.html
imprimatur/templates/run.html
imprimatur-0.24.0.dist-info/METADATA
imprimatur-0.24.0.dist-info/WHEEL
imprimatur-0.24.0.dist-info/entry_points.txt
imprimatur-0.24.0.dist-info/top_level.txt
imprimatur-0.24.0.dist-info/RECORD
