Metadata-Version: 2.1
Name: imprimatur
Version: 0.24.0
Summary: Functional testing tool for web applications.
Home-page: https://github.com/tlocke/imprimatur
Author: Tony Locke
Author-email: tlocke@tlocke.org.uk
License: GPL
Keywords: functional testing web
Platform: UNKNOWN
Classifier: Development Status :: 4 - Beta
Classifier: Intended Audience :: Developers
Classifier: License :: OSI Approved :: GNU General Public License (GPL)
Classifier: Programming Language :: Python
Classifier: Programming Language :: Python :: 3
Classifier: Programming Language :: Python :: 3.5
Classifier: Programming Language :: Python :: Implementation
Classifier: Programming Language :: Python :: Implementation :: CPython
Classifier: Programming Language :: Python :: Implementation :: PyPy
Classifier: Operating System :: OS Independent
Requires-Dist: flask (==1.1.2)
Requires-Dist: requests (==2.23.0)
